seoulai_gym/__init__.py
seoulai_gym/envs/__init__.py
seoulai_gym/envs/base_agent.py
seoulai_gym/envs/checkers/__init__.py
seoulai_gym/envs/checkers/agents.py
seoulai_gym/envs/checkers/base.py
seoulai_gym/envs/checkers/board.png
seoulai_gym/envs/checkers/board.py
seoulai_gym/envs/checkers/checkers.py
seoulai_gym/envs/checkers/checkers_test.py
seoulai_gym/envs/checkers/graphics.py
seoulai_gym/envs/checkers/rules.py
seoulai_gym/envs/checkers/utils.py
seoulai_gym/envs/mighty/agents.py
seoulai_gym/envs/mighty/base.py
seoulai_gym/envs/mighty/board.py
seoulai_gym/envs/mighty/graphics.py
seoulai_gym/envs/mighty/mighty.py
seoulai_gym/envs/mighty/rules.py
seoulai_gym/envs/mighty/agent/AlangAgent.py
seoulai_gym/envs/mighty/agent/BossAgent.py
seoulai_gym/envs/mighty/agent/RandomAgent.py
seoulai_gym/envs/mighty/resource/bck.png
seoulai_gym/envs/mighty/resource/c-0.png
seoulai_gym/envs/mighty/resource/c-1.png
seoulai_gym/envs/mighty/resource/c-2.png
seoulai_gym/envs/mighty/resource/c-3.png
seoulai_gym/envs/mighty/resource/c-4.png
seoulai_gym/envs/mighty/resource/c-5.png
seoulai_gym/envs/mighty/resource/c-6.png
seoulai_gym/envs/mighty/resource/c-7.png
seoulai_gym/envs/mighty/resource/c-8.png
seoulai_gym/envs/mighty/resource/c-9.png
seoulai_gym/envs/mighty/resource/c-j.png
seoulai_gym/envs/mighty/resource/c-k.png
seoulai_gym/envs/mighty/resource/c-q.png
seoulai_gym/envs/mighty/resource/credit.png
seoulai_gym/envs/mighty/resource/d-0.png
seoulai_gym/envs/mighty/resource/d-1.png
seoulai_gym/envs/mighty/resource/d-2.png
seoulai_gym/envs/mighty/resource/d-3.png
seoulai_gym/envs/mighty/resource/d-4.png
seoulai_gym/envs/mighty/resource/d-5.png
seoulai_gym/envs/mighty/resource/d-6.png
seoulai_gym/envs/mighty/resource/d-7.png
seoulai_gym/envs/mighty/resource/d-8.png
seoulai_gym/envs/mighty/resource/d-9.png
seoulai_gym/envs/mighty/resource/d-j.png
seoulai_gym/envs/mighty/resource/d-k.png
seoulai_gym/envs/mighty/resource/d-q.png
seoulai_gym-0.1.2.dist-info/METADATA
seoulai_gym-0.1.2.dist-info/RECORD
seoulai_gym-0.1.2.dist-info/WHEEL
seoulai_gym-0.1.2.dist-info/top_level.txt
