Metadata-Version: 2.1
Name: seoulai-gym
Version: 0.1.2
Summary: The Seoul AI Gym: Seoul AI Gym is a toolkit for developing AI algorithms.
Home-page: https://github.com/seoulai/gym
Author: Seoul AI
Author-email: m.kersner@gmail.com
License: The MIT License
Keywords: gym,ai,machine-learning,artificial-intelligence
Platform: UNKNOWN
Requires-Dist: pygame (>=1.9.3)
Requires-Dist: numpy (>=1.14.2)
Requires-Dist: pytest (>=3.6.0)
Requires-Dist: flake8 (>=3.5.0)
Requires-Dist: PyQt5 (>=5)
Requires-Dist: pandas (>=0.23.4)
Requires-Dist: matplotlib (>=2.2.3)
Requires-Dist: flake8-quotes (>=1.0.0)
